{
    "config": {
        "Shift_Differential": {
            "require": {
                "AND": [
                    { "Shift_Differential_Eligibility": "Yes" }
                ]
            }
        },
        "Union_Dues_Eligibility": {
            "require": {
                "AND": [
                    { "JobCode_Union": "Yes" }
                ]
            },
            "visible": {
                "AND": [
                    { "JobCode_Union": "Yes" }
                ]
            }
        },
        "Union_Dues": {
            "require": {
                "AND": [
                    { "JobCode_Union": "Yes" }
                ]
            },
            "visible": {
                "AND": [
                    { "JobCode_Union": "Yes" }
                ]
            }
        },
        "Deduction_Frequency": {
            "require": {
                "AND": [
                    { "JobCode_Union": "Yes" }
                ]
            },
            "visible": {
                "AND": [
                    { "JobCode_Union": "Yes" }
                ]
            }
        },
        "Entitlement_Exception_Option": {
            "require": {
                "NOR": [
                    { "Entitlement_Option": "None" },
                    { "Entitlement_Option": "Standard" }
                ]
            },
            "readonly": {
                "OR": [
                    { "Entitlement_Option": "None" },
                    { "Entitlement_Option": "Standard" }
                ]
            }
        },
        "Entitlement_Exception": {
            "require": {
                "NOR": [
                    { "Entitlement_Option": "None" },
                    { "Entitlement_Option": "Standard" }
                ]
            },
            "readonly": {
                "OR": [
                    { "Entitlement_Option": "None" },
                    { "Entitlement_Option": "Standard" }
                ]
            }
        },
        "Annuity": {
            "require": {
                "AND": [
                    { "JobCode_Union": "Yes" },
                    { "OpCo": "Cooper Electric" }
                ]
            },
            "visible": {
                "AND": [
                    { "JobCode_Union": "Yes" },
                    { "OpCo": "Cooper Electric" }
                ]
            }
        },
        "Retirement": {
            "require": {
                "AND": [
                    { "JobCode_Union": "Yes" },
                    { "OpCo": "Cooper Electric" }
                ]
            },
            "visible": {
                "AND": [
                    { "JobCode_Union": "Yes" },
                    { "OpCo": "Cooper Electric" }
                ]
            }
        },
        "FICA_Reimb": {
            "require": {
                "AND": [
                    { "JobCode_Union": "Yes" },
                    { "OpCo": "Cooper Electric" }
                ]
            },
            "visible": {
                "AND": [
                    { "JobCode_Union": "Yes" },
                    { "OpCo": "Cooper Electric" }
                ]
            }
        },
        "Education": {
            "require": {
                "AND": [
                    { "JobCode_Union": "Yes" },
                    { "OpCo": "Cooper Electric" }
                ]
            },
            "visible": {
                "AND": [
                    { "JobCode_Union": "Yes" },
                    { "OpCo": "Cooper Electric" }
                ]
            }
        },
        "Health_Reimb": {
            "require": {
                "AND": [
                    { "JobCode_Union": "Yes" },
                    { "OpCo": "Cooper Electric" }
                ]
            },
            "visible": {
                "AND": [
                    { "JobCode_Union": "Yes" },
                    { "OpCo": "Cooper Electric" }
                ]
            }
        },
        "Workers_Comp": {
            "require": {
                "AND": [
                    { "JobCode_Union": "Yes" },
                    { "OpCo": "Cooper Electric" }
                ]
            },
            "visible": {
                "AND": [
                    { "JobCode_Union": "Yes" },
                    { "OpCo": "Cooper Electric" }
                ]
            }
        }
    }
}
